LICENSE
README.md
setup.py
eqlink/__init__.py
eqlink.egg-info/PKG-INFO
eqlink.egg-info/SOURCES.txt
eqlink.egg-info/dependency_links.txt
eqlink.egg-info/requires.txt
eqlink.egg-info/top_level.txt
eqlink/components/__init__.py
eqlink/components/link_list.py
eqlink/components/load_conf.py
eqlink/components/protocol.py
eqlink/components/read_conf.py
eqlink/components/read_module.py
eqlink/components/remote_server.py
eqlink/main/__init__.py
eqlink/main/clent.py
eqlink/main/register.py
eqlink/main/server.py