Metadata-Version: 2.1
Name: eqlink
Version: 0.0.16
Summary: 注册中心
Home-page: https://github.com/enqiangjing/eqlink
Author: enqiang
Author-email: enqiangjing@163.com
License: MIT license
Keywords: eqlink,Registration Center,eqsmart
Platform: any
License-File: LICENSE
